README.md
setup.cfg
setup.py
distributions_AnthonyGoh7/Binomialdistribution.py
distributions_AnthonyGoh7/Gaussiandistribution.py
distributions_AnthonyGoh7/Generaldistribution.py
distributions_AnthonyGoh7/__init__.py
distributions_AnthonyGoh7.egg-info/PKG-INFO
distributions_AnthonyGoh7.egg-info/SOURCES.txt
distributions_AnthonyGoh7.egg-info/dependency_links.txt
distributions_AnthonyGoh7.egg-info/not-zip-safe
distributions_AnthonyGoh7.egg-info/top_level.txt